pyfdbg/__init__.py
pyfdbg/__main__.py
pyfdbg/data.py
pyfdbg/stdlib.py
pyfdbg-0.1.0.dist-info/LICENSE
pyfdbg-0.1.0.dist-info/METADATA
pyfdbg-0.1.0.dist-info/WHEEL
pyfdbg-0.1.0.dist-info/entry_points.txt
pyfdbg-0.1.0.dist-info/top_level.txt
pyfdbg-0.1.0.dist-info/RECORD
