Metadata-Version: 2.1
Name: pyfdbg
Version: 0.1.0
Summary: 一个简单且强大、易于使用的调试器
Author: DashBing
Author-email: mcbbkf@outlook.com
Classifier: Development Status :: 4 - Beta
Classifier: Programming Language :: Python :: Implementation :: CPython
Classifier: Programming Language :: Python :: 3.11
Classifier: License :: OSI Approved :: MIT License
Classifier: Operating System :: OS Independent
Classifier: Natural Language :: Chinese (Simplified)
Requires-Python: >=3.9
License-File: LICENSE
Requires-Dist: phap (>=3.1.0)
